[
  {
    "name": "BULAŞIK MAKINASI REZİSTANSI",
    "url": "https://www.hasmar.com.tr/details/7/159/bulasik-makinasi-rezistansi",
    "image_url": "https://www.hasmar.com.tr/images/product/050e6cc6-e92f-.jpg",
    "saved_image_path": "output/images/BULAŞIK MAKINASI REZİSTANSI.jpg"
  },
  {
    "name": "BULAŞIK MAKINASI REZİSTANSI",
    "url": "https://www.hasmar.com.tr/details/7/160/bulasik-makinasi-rezistansi",
    "image_url": "https://www.hasmar.com.tr/images/product/373dd2d6-1da9-.jpg",
    "saved_image_path": "output/images/BULAŞIK MAKINASI REZİSTANSI.jpg"
  },
  {
    "name": "BULAŞIK MAKINASI REZİSTANSI",
    "url": "https://www.hasmar.com.tr/details/7/161/bulasik-makinasi-rezistansi",
    "image_url": "https://www.hasmar.com.tr/images/product/96714aa9-2eae-.jpg",
    "saved_image_path": "output/images/BULAŞIK MAKINASI REZİSTANSI.jpg"
  },
  {
    "name": "BULAŞIK MAKINASI REZİSTANSI",
    "url": "https://www.hasmar.com.tr/details/7/162/bulasik-makinasi-rezistansi",
    "image_url": "https://www.hasmar.com.tr/images/product/ad87ce8c-af68-.jpg",
    "saved_image_path": "output/images/BULAŞIK MAKINASI REZİSTANSI.jpg"
  },
  {
    "name": "BULAŞIK MAKINASI REZİSTANSI",
    "url": "https://www.hasmar.com.tr/details/7/163/bulasik-makinasi-rezistansi",
    "image_url": "https://www.hasmar.com.tr/images/product/ed4e8aef-addd-.jpg",
    "saved_image_path": "output/images/BULAŞIK MAKINASI REZİSTANSI.jpg"
  },
  {
    "name": "UÇGEN KAFA BULAŞIK MAKİNASI REZİSTANSI",
    "url": "https://www.hasmar.com.tr/details/7/164/ucgen-kafa-bulasik-makinasi-rezistansi",
    "image_url": "https://www.hasmar.com.tr/images/product/b20a1d23-553b-.jpg",
    "saved_image_path": "output/images/UÇGEN KAFA BULAŞIK MAKİNASI REZİSTANSI.jpg"
  },
  {
    "name": "ÇAMAŞIR MAKINASI REZİSTANSI",
    "url": "https://www.hasmar.com.tr/details/7/165/camasir-makinasi-rezistansi",
    "image_url": "https://www.hasmar.com.tr/images/product/50003c1b-30de-.jpg",
    "saved_image_path": "output/images/ÇAMAŞIR MAKINASI REZİSTANSI.jpg"
  },
  {
    "name": "ÇAMAŞIR MAKINASI REZİSTANSI",
    "url": "https://www.hasmar.com.tr/details/7/166/camasir-makinasi-rezistansi",
    "image_url": "https://www.hasmar.com.tr/images/product/c85f62fc-62a2-.jpg",
    "saved_image_path": "output/images/ÇAMAŞIR MAKINASI REZİSTANSI.jpg"
  },
  {
    "name": "ÇAMAŞIR MAKINASI REZİSTANSI",
    "url": "https://www.hasmar.com.tr/details/7/167/camasir-makinasi-rezistansi",
    "image_url": "https://www.hasmar.com.tr/images/product/f703a0a7-5854-.jpg",
    "saved_image_path": "output/images/ÇAMAŞIR MAKINASI REZİSTANSI.jpg"
  }
]